orgilib/__init__.py
orgilib/chart.py
orgilib-0.0.6.dist-info/LICENSE.txt
orgilib-0.0.6.dist-info/METADATA
orgilib-0.0.6.dist-info/WHEEL
orgilib-0.0.6.dist-info/top_level.txt
orgilib-0.0.6.dist-info/RECORD
