Metadata-Version: 2.1
Name: orgilib
Version: 0.0.6
Summary: ORG-A py module
Home-page: http://www.org-i.com/
Author: Henry.Kim
Author-email: hjkim@org-i.com
Classifier: Programming Language :: Python :: 3
Classifier: License :: OSI Approved :: MIT License
Classifier: Operating System :: OS Independent
Requires-Python: >=3.8
License-File: LICENSE.txt
Requires-Dist: pandas (>=1.4.4)
